phySyncFirmata/__init__.py
phySyncFirmata/boards.py
phySyncFirmata/mockup.py
phySyncFirmata/phySyncFirmata.py
phySyncFirmata/util.py
phySyncFirmata-3.0.3.dist-info/LICENSE
phySyncFirmata-3.0.3.dist-info/METADATA
phySyncFirmata-3.0.3.dist-info/WHEEL
phySyncFirmata-3.0.3.dist-info/top_level.txt
phySyncFirmata-3.0.3.dist-info/RECORD
